fl4health/__init__.py
fl4health/checkpointing/__init__.py
fl4health/checkpointing/checkpointer.py
fl4health/checkpointing/client_module.py
fl4health/checkpointing/opacus_checkpointer.py
fl4health/checkpointing/server_module.py
fl4health/checkpointing/state_checkpointer.py
fl4health/client_managers/__init__.py
fl4health/client_managers/base_sampling_manager.py
fl4health/client_managers/fixed_sampling_client_manager.py
fl4health/client_managers/fixed_without_replacement_manager.py
fl4health/client_managers/poisson_sampling_manager.py
fl4health/clients/__init__.py
fl4health/clients/adaptive_drift_constraint_client.py
fl4health/clients/apfl_client.py
fl4health/clients/basic_client.py
fl4health/clients/clipping_client.py
fl4health/clients/constrained_fenda_client.py
fl4health/clients/ditto_client.py
fl4health/clients/ensemble_client.py
fl4health/clients/evaluate_client.py
fl4health/clients/fed_pca_client.py
fl4health/clients/fed_prox_client.py
fl4health/clients/fedbn_client.py
fl4health/clients/fedper_client.py
fl4health/clients/fedpm_client.py
fl4health/clients/fedrep_client.py
fl4health/clients/fenda_client.py
fl4health/clients/fenda_ditto_client.py
fl4health/clients/flash_client.py
fl4health/clients/gpfl_client.py
fl4health/clients/instance_level_dp_client.py
fl4health/clients/model_merge_client.py
fl4health/clients/moon_client.py
fl4health/clients/mr_mtl_client.py
fl4health/clients/nnunet_client.py
fl4health/clients/partial_weight_exchange_client.py
fl4health/clients/perfcl_client.py
fl4health/clients/scaffold_client.py
fl4health/clients/tabular_data_client.py
fl4health/clients/deep_mmd_clients/__init__.py
fl4health/clients/deep_mmd_clients/ditto_deep_mmd_client.py
fl4health/clients/deep_mmd_clients/mr_mtl_deep_mmd_client.py
fl4health/clients/flexible/__init__.py
fl4health/clients/flexible/base.py
fl4health/clients/flexible/nnunet.py
fl4health/clients/mkmmd_clients/__init__.py
fl4health/clients/mkmmd_clients/ditto_mkmmd_client.py
fl4health-0.4.2.dist-info/METADATA
fl4health-0.4.2.dist-info/WHEEL
fl4health-0.4.2.dist-info/licenses/LICENSE.md
fl4health-0.4.2.dist-info/RECORD
