Metadata-Version: 2.4
Name: fl4health
Version: 0.4.2
Summary: Federated Learning for Health
Author-email: Vector AI Engineering <fl4health@vectorinstitute.ai>
License: Apache-2.0
License-File: LICENSE.md
Classifier: License :: OSI Approved :: Apache Software License
Classifier: Operating System :: OS Independent
Classifier: Programming Language :: Python :: 3
Requires-Python: <3.11,>=3.10.0
Requires-Dist: acvl-utils==0.2
Requires-Dist: aiohttp<4.0.0,>=3.13.3
Requires-Dist: cmake<4.0.0,>=3.31.6
Requires-Dist: dm-tree<0.2.0,>=0.1.9
Requires-Dist: dp-accounting<0.5.0,>=0.4.3
Requires-Dist: ecos<3.0.0,>=2.0.7.post1
Requires-Dist: fastapi<1.0.0,>=0.121.0
Requires-Dist: flwr-datasets<1.0.0,>=0.5.0
Requires-Dist: flwr<1.19.0,>=1.18.0
Requires-Dist: grpcio!=1.64.2,!=1.65.1,!=1.65.2,!=1.65.4,<2.0.0,>=1.60.0
Requires-Dist: jupyter-core<6.0.0,>=5.8.1
Requires-Dist: matplotlib<4.0.0,>=3.10.1
Requires-Dist: monai<2.0.0,>=1.5.1
Requires-Dist: nnunetv2<3.0.0,>=2.3.1
Requires-Dist: numpy<2.0,>=1.24
Requires-Dist: opacus<2.0.0,>=1.3.0
Requires-Dist: pandas<3.0,>=2.0
Requires-Dist: peft<1.0.0,>=0.14.0
Requires-Dist: pyarrow<18.0.0,>=17.0.0
Requires-Dist: pyasn1>=0.6.2
Requires-Dist: pympler<2.0,>=1.1
Requires-Dist: qpth<0.1.0,>=0.0.16
Requires-Dist: scikit-learn==1.5.0
Requires-Dist: starlette<1.0.0,>=0.49.1
Requires-Dist: torch==2.6.0
Requires-Dist: torchmetrics<2.0.0,>=1.3.0
Requires-Dist: tornado<7.0,>=6.5
Requires-Dist: urllib3<3.0.0,>=2.6.3
Requires-Dist: wandb<1.0.0,>=0.18.0
